mermaid_builder/__init__.py
mermaid_builder/flowchart.py
mermaid_builder/sequence_diagram.py
mermaid_builder-0.0.2.dist-info/LICENSE
mermaid_builder-0.0.2.dist-info/METADATA
mermaid_builder-0.0.2.dist-info/WHEEL
mermaid_builder-0.0.2.dist-info/top_level.txt
mermaid_builder-0.0.2.dist-info/RECORD
