Metadata-Version: 2.1
Name: mermaid_builder
Version: 0.0.2
Summary: MermaidJS markup builder for Python
Author-email: Roman Inozemtsev <roman.inozemtsev+github@gmail.com>
Project-URL: Homepage, https://github.com/romaninozemtsev/python-mermaid-builder
Classifier: Programming Language :: Python :: 3
Classifier: License :: OSI Approved :: MIT License
Classifier: Operating System :: OS Independent
Requires-Python: >=3.5
License-File: LICENSE
